ckanext_valeria-1.0.9-py3.8-nspkg.pth
ckanext/valeria/__init__.py
ckanext/valeria/plugin.py
ckanext/valeria/assets/style.css
ckanext/valeria/assets/webassets.yml
ckanext/valeria/public/images/VALERIA_Symbole_Blanc.svg
ckanext/valeria/public/images/VALERIA_Symbole_Gris_Pale.svg
ckanext/valeria/public/images/VALERIA_Symbole_Noir.svg
ckanext/valeria/public/images/VALERIA_Texte_Blanc.svg
ckanext/valeria/public/images/VALERIA_Texte_Couleur.svg
ckanext/valeria/public/images/VALERIA_Texte_Noir.svg
ckanext/valeria/public/images/VALERIA_ang_coul.svg
ckanext/valeria/public/images/VALERIA_fr_coul.png
ckanext/valeria/public/images/VALERIA_fr_coul.svg
ckanext/valeria/public/images/background-image.jpg
ckanext/valeria/public/images/logo-ulaval-blanc.svg
ckanext/valeria/public/images/logo-ulaval.svg
ckanext/valeria/templates/base.html
ckanext/valeria/templates/footer.html
ckanext/valeria/templates/header.html
ckanext/valeria/templates/group/read.html
ckanext/valeria/templates/group/read_base.html
ckanext/valeria/templates/home/snippets/promoted.html
ckanext/valeria/templates/home/snippets/search.html
ckanext/valeria/templates/home/snippets/stats.html
ckanext/valeria/templates/organization/read.html
ckanext/valeria/templates/package/base.html
ckanext/valeria/templates/package/read_base.html
ckanext/valeria/templates/snippets/facet_list.html
ckanext/valeria/templates/snippets/group.html
ckanext/valeria/templates/snippets/organization.html
ckanext/valeria/templates/snippets/organization_item.html
ckanext_valeria-1.0.9.dist-info/LICENSE
ckanext_valeria-1.0.9.dist-info/METADATA
ckanext_valeria-1.0.9.dist-info/WHEEL
ckanext_valeria-1.0.9.dist-info/entry_points.txt
ckanext_valeria-1.0.9.dist-info/namespace_packages.txt
ckanext_valeria-1.0.9.dist-info/top_level.txt
ckanext_valeria-1.0.9.dist-info/RECORD
