Metadata-Version: 2.1
Name: ckanext-valeria
Version: 1.0.9
Summary: Valeria Theme
Home-page: https://catalogue.valeria.science/
Author: Dave Berthiaume
Author-email: dave.berthiaume@dti.ulaval.ca
License: UNKNOWN
Keywords: CKAN THEME
Platform: UNKNOWN
